odoo/addons/stock_rule_mto_vendor_purchase_type/README.rst
odoo/addons/stock_rule_mto_vendor_purchase_type/__init__.py
odoo/addons/stock_rule_mto_vendor_purchase_type/__manifest__.py
odoo/addons/stock_rule_mto_vendor_purchase_type/models/__init__.py
odoo/addons/stock_rule_mto_vendor_purchase_type/models/stock_rule.py
odoo/addons/stock_rule_mto_vendor_purchase_type/static/description/icon.png
odoo12_addon_stock_rule_mto_vendor_purchase_type-12.0.1.0.0.dist-info/METADATA
odoo12_addon_stock_rule_mto_vendor_purchase_type-12.0.1.0.0.dist-info/WHEEL
odoo12_addon_stock_rule_mto_vendor_purchase_type-12.0.1.0.0.dist-info/top_level.txt
odoo12_addon_stock_rule_mto_vendor_purchase_type-12.0.1.0.0.dist-info/RECORD
