Metadata-Version: 2.1
Name: odoo12-addon-stock_rule_mto_vendor_purchase_type
Version: 12.0.1.0.0
Summary: Purchase order type from vendor in POs from stock rule or MTO.
Home-page: https://www.sygel.es
Author: Sygel, Odoo Community Association (OCA)
Author-email: support@odoo-community.org
License: AGPL-3
Classifier: Programming Language :: Python
Classifier: Framework :: Odoo
Classifier: Framework :: Odoo :: 12.0
Classifier: License :: OSI Approved :: GNU Affero General Public License v3
Requires-Python: >=3.5
Requires-Dist: odoo<12.1dev,>=12.0a
